setup.cfg
setup.py
bin/mic
microscopium/__init__.py
microscopium/_util.py
microscopium/cluster.py
microscopium/features.py
microscopium/io.py
microscopium/main.py
microscopium/metrics.py
microscopium/pathutils.py
microscopium/preprocess.py
microscopium.egg-info/PKG-INFO
microscopium.egg-info/SOURCES.txt
microscopium.egg-info/dependency_links.txt
microscopium.egg-info/top_level.txt
microscopium/screens/__init__.py
microscopium/screens/cellomics.py
microscopium/screens/myofusion.py