Metadata-Version: 1.0
Name: microscopium
Version: 0.1.dev0
Summary: Clustering of High Content Screen Images
Home-page: https://github.com/microscopium/microscopium
Author: Juan Nunez-Iglesias
Author-email: juan.n@unimelb.edu.au
License: BSD 3-clause
Platform: UNKNOWN
